locid/__init__.py
locid/ble.py
locid/cli.py
locid/json_rpc_io.py
locid/locid.py
locid/locid_jsonrpc_proto_async.py
locid/locid_jsonrpc_proto_sync.py
locid/rtb_serial_protocol.py
locid-0.0.9.dist-info/LICENSE
locid-0.0.9.dist-info/METADATA
locid-0.0.9.dist-info/WHEEL
locid-0.0.9.dist-info/entry_points.txt
locid-0.0.9.dist-info/top_level.txt
locid-0.0.9.dist-info/RECORD
