Metadata-Version: 2.1
Name: locid
Version: 0.0.9
Summary: LOC.id python bindings
Home-page: https://locid.org/
Author: Christian Baumgart
Author-email: christian.baumgart@rtb-elektronik.de
License: BSD 3-clause
Classifier: Programming Language :: Python :: 3
Classifier: License :: OSI Approved :: BSD License
Classifier: Operating System :: OS Independent
Requires-Python: >=3.7
License-File: LICENSE
Requires-Dist: pyserial
Requires-Dist: bleak
